{
  "main": [
    {
      "category": "Lúa Gạo",
      "date": "27 | 12 | 2023",
      "title": "Chính Phủ Ấn Độ Có Thể Cấm Xuất Khẩu Gạo...",
      "image": "img/rice_plant.jpg"
    },
    {
      "category": "Lúa Gạo",
      "date": "27 | 12 | 2023",
      "title": "VIỆT NAM ĐÃ CHI 4,27 TỶ USD NHẬP KHẨU THỨC ĂN CHĂN NUÔI GIA SÚC VÀ NGUYÊN LIỆU...",
      "image": "img/rice_plant_2.jpg"
    },
    {
      "category": "Cà Phê",
      "date": "27 | 12 | 2023",
      "title": "ETHIOPIA CẤM XUẤT KHẨU, GIÁ CÀ PHÊ THẾ GIỚI CÓ THỂ TĂNG VỌT...",
      "image": "img/coffee.jpg"
    }
  ],
  "block main": [
    {
      "category": "Lúa Gạo",
      "date": "27 | 12 | 2023",
      "title": "LIÊN KẾT VỚI HƠN 3.000 NÔNG DÂN LÀM...",
      "image": "img/coffee_2.jpg"
    },
    {
      "category": "Lúa Gạo",
      "date": "27 | 12 | 2023",
      "title": "Cao Su Rớt Giá Do Siết chặt đầu ra...",
      "image": "img/cao_su.jpg"
    },
    {
      "category": "Cà Phê",
      "date": "27 | 12 | 2023",
      "title": "Thiếu hụt nhân công thu...",
      "image": "img/cao_su_2.png"
    },
    {
      "category": "Cà Phê",
      "date": "27 | 12 | 2023",
      "title": " Báo cáo thị trường xuất khẩu quý...",
      "image": "img/report.png"
    }
  ],
  "feature": [
    {
      "category": "Cao Su",
      "date": "27 | 12 | 2023",
      "title": "Quan chức Tổng cục Lâm nghiệp: Cây...",
      "image": "img/feature_1.jpg"
    },
    {
      "category": "Lúa Gạo",
      "date": "27 | 12 | 2023",
      "title": "Cơ hội vàng cho các doanh nghiệp...",
      "image": "img/feature_2.jpg"
    },
    {
      "category": "Lúa Gạo",
      "date": "27 | 12 | 2023",
      "title": "Doanh nghiệp ngành gạo đón “trợ lực”...",
      "image": "img/feature_3.png"
    },
    {
      "category": "Cà Phê",
      "date": "27 | 12 | 2023",
      "title": "Ngành cà phê Việt Nam trong những năm qua",
      "image": "img/feature_4.jpg"
    },
    {
      "category": "Cao Su",
      "date": "27 | 12 | 2023",
      "title": "Hướng Dẫn Cách Lấy Mủ Cao Su Đúng Kỹ Thuật",
      "image": "img/feature_5.jpg"
    }
  ],
  "latest": [
    {
      "category": "Lúa Gạo",
      "date": "11 | 12 | 2023",
      "title": "GẠO VIỆT QUAY ĐẦU GIẢM GIÁ VẪN ĐẮT NHẤT THẾ GIỚI, GẠO THÁI LAN TĂNG MẠNH",
      "brief": "Đang neo ở mức đỉnh, giá gạo Việt xuất khẩu quay đầu giảm sau tin đạt giải Gạo ngon nhất thế giới năm 2023...",
      "image": "img/latest_1.jpg"
    },
    {
      "category": "Cà Phê",
      "date": "18 | 12 | 2023",
      "title": "GIÁ LIÊN TỤC TĂNG VÀO NEO Ở MỨC CAO, NGƯỜI DÂN TRỒNG CÀ PHÊ TRÚNG ĐẬM",
      "brief": "Giá cà phê nội địa đạt gần 70.000 đồng/kg. Đây là điều chưa từng xảy ra trong lịch sử ngành cà phê Việt Nam.",
      "image": "img/latest_2.jpg"
    },
    {
      "category": "Cao Su",
      "date": "15 | 12 | 2023",
      "title": "THỊ PHẦN CAO SU CỦA VIỆT NAM ĐANG BỊ THU HẸP TẠI THỊ TRƯỜNG ẤN",
      "brief": "11 tháng năm 2023, xuất khẩu cao su đạt trên 1,87 triệu tấn, trị giá 2,51 tỷ USD. Tuy nhiên, thị phần cao su...",
      "image": "img/latest_3.jpg"
    },
    {
      "category": "Lúa Gạo",
      "date": "18 | 12 | 2023",
      "title": "THÀNH LẬP HIỆP HỘI NGÀNH HÀNG LÚA GẠO VIỆT NAM",
      "brief": "Lúa gạo có thêm một hiệp hội là Hiệp hội Ngành hàng lúa gạo Việt Nam, quy tụ các thành phần trong chuỗi giá...",
      "image": "img/latest_4.jpg"
    }
  ],
  "left-other": [
    {
      "category": "Cà Phê",
      "date": "27 | 12 | 2023",
      "title": "Xuất khẩu cà phê: Điểm sáng trong nhiều thách thức",
      "image": "img/other_1.png"
    },
    {
      "category": "Lúa Gạo",
      "date": "27 | 12 | 2023",
      "title": "Cân đối nguồn lúa, gạo phục vụ nhu cầu trong nước, xuất...",
      "image": "img/other_2.png"
    }
  ],
  "right-other": [
    {
      "category": "Cao su",
      "date": "27 | 12 | 2023",
      "title": "Cao su xuất khẩu hầu hết sang Trung Quốc; Cấp bách bảo...",
      "image": "img/other_3.jpg"
    },
    {
      "category": "Cà Phê",
      "date": "27 | 12 | 2023",
      "title": "Ngành cà phê cần huy động được các nguồn lực để phát...",
      "image": "img/other_4.jpg"
    }
  ],
  "market": [
    {
      "category": "Cà Phê",
      "date": "27 | 12 | 2023",
      "title": "Giá cà phê hôm nay 27/12: Duy trì ở mức cao",
      "image": "img/market_1.jpg"
    },
    {
      "category": "Cao Su",
      "date": "27 | 12 | 2023",
      "title": "Giá cao su hôm nay 27/12: Tiếp tục tăng...",
      "image": "img/market_2.jpg"
    },
    {
      "category": "Lúa Gạo",
      "date": "27 | 12 | 2023",
      "title": "Giá lúa gạo hôm nay 27/12: Các mặt hàng đi ngang",
      "image": "img/market_3.jpg"
    }
  ]
}

